mechanicus/__init__.py
mechanicus/downloader.py
mechanicus/core/__init__.py
mechanicus/core/executor.py
mechanicus-0.0.2.dist-info/METADATA
mechanicus-0.0.2.dist-info/WHEEL
mechanicus-0.0.2.dist-info/top_level.txt
mechanicus-0.0.2.dist-info/RECORD
