Metadata-Version: 2.1
Name: mechanicus
Version: 0.0.2
Summary: UNKNOWN
Home-page: https://bitbucket.org/shmyga/mechanicus
Author: shmyga
Author-email: shmyga.z@gmail.com
License: MIT
Platform: UNKNOWN
Requires-Python: >=3.7
Requires-Dist: aiohttp (>=3)
Requires-Dist: aiofiles (>=0)
